flockai/__init__.py
flockai/PyCatascopia/Decorators.py
flockai/PyCatascopia/Metrics.py
flockai/PyCatascopia/Probe.py
flockai/PyCatascopia/__init__.py
flockai/PyCatascopia/probelib/ExampleProbe.py
flockai/PyCatascopia/probelib/ProcessProbe.py
flockai/PyCatascopia/probelib/__init__.py
flockai/interfaces/__init__.py
flockai/interfaces/drone.py
flockai/interfaces/energy.py
flockai/interfaces/flockai_ml.py
flockai/interfaces/robot.py
flockai/interfaces/sensor.py
flockai/models/__init__.py
flockai/models/base/__init__.py
flockai/models/base/base_station.py
flockai/models/battery/__init__.py
flockai/models/battery/battery.py
flockai/models/devices/__init__.py
flockai/models/devices/device_enums.py
flockai/models/drones/__init__.py
flockai/models/drones/autopilot_controlled_drone.py
flockai/models/drones/keyboard_controller_drone.py
flockai/models/energy/__init__.py
flockai/models/energy/energy.py
flockai/models/probes/__init__.py
flockai/models/probes/flockai_probe.py
flockai/models/sensors/__init__.py
flockai/models/sensors/humidity.py
flockai/models/sensors/temperature.py
flockai/models/simulations/__init__.py
flockai/models/simulations/simulation_config.py
flockai/patterns/__init__.py
flockai/patterns/singleton.py
flockai/services/__init__.py
flockai/utils/__init__.py
flockai/utils/graphics.py
flockai/utils/intensive_thread.py
flockai/utils/string_generator.py
flockai/webots_controllers/__init__.py
flockai/webots_controllers/flockai_controller.py
flockai/webots_controllers/mavic2dji.py
flockai-0.1.18.dist-info/LICENSE
flockai-0.1.18.dist-info/METADATA
flockai-0.1.18.dist-info/WHEEL
flockai-0.1.18.dist-info/top_level.txt
flockai-0.1.18.dist-info/RECORD
