Metadata-Version: 2.1
Name: flockai
Version: 0.1.18
Summary: A machine learning webots extension
Home-page: https://github.com/unic-ailab/flockai-working
Author: kosnet
Author-email: kosnet@kosnet.com
License: UNKNOWN
Platform: UNKNOWN
Classifier: Programming Language :: Python :: 3
Classifier: License :: OSI Approved :: MIT License
Classifier: Operating System :: OS Independent
Requires-Python: >=3.6
